{
    "analysis_time": "2026-05-20 16:01",
    "report_type": "Regular Report",
    "results": [
        {
            "종목명": "DB손해보험",
            "증권사": "iM증권",
            "레포트 제목": "업종의 기대 요인을 모두 포괄하는 선택",
            "발행일자": "2026-05-20",
            "목표주가": "220,000원",
            "평가방식": "이익 체력 및 성장 기대",
            "투자포인트": [
                "1Q26 실적 부진은 일회성 요인이 강하며, 하반기 실손 제도 개선 및 배당 매력 부각으로 주가 반등 기대",
                "이익 체력 대비 최근 주가 조정은 과도하다는 판단"
            ],
            "현재가": "156,300원",
            "현재시총": "102,377억",
            "Upside": 40.8,
            "목표시총": "144,100억",
            "source_type": "butler_works"
        },
        {
            "종목명": "한국금융지주",
            "증권사": "iM증권",
            "레포트 제목": "IB-AM이 지나면",
            "발행일자": "2026-05-20",
            "목표주가": "310,000원",
            "평가방식": "PER 기준 저평가",
            "투자포인트": [
                "IB(기업금융)와 AM(자산관리) 부문 모두 높은 경쟁력을 바탕으로 견조한 이익 체력 전망",
                "2026년 예상 ROE 20%의 높은 수익성 대비, PER 5.3배의 업종 내 가장 낮은 밸류에이션 매력 보유"
            ],
            "현재가": "232,500원",
            "현재시총": "129,562억",
            "Upside": 33.3,
            "목표시총": "172,750억",
            "source_type": "butler_works"
        },
        {
            "종목명": "에스엘",
            "증권사": "대신증권",
            "레포트 제목": "수익성, 성장, 주주환원 모두 합격",
            "발행일자": "2026-05-20",
            "목표주가": "86,000원",
            "평가방식": "이익 체력 및 성장, 주주환원 정책 고려",
            "투자포인트": [
                "1Q26 고객 보상금 및 판매 호조로 어닝 서프라이즈를 기록했으며, 2Q26에도 신차 효과로 1,300억 원대 영업이익 달성 전망",
                "견조한 이익 체력, 신사업 기대감, 2026년 배당성향 40% 등 주주환원 정책을 고려"
            ],
            "현재가": "58,900원",
            "현재시총": "27,358억",
            "Upside": 46.0,
            "목표시총": "39,945억",
            "source_type": "butler_works"
        },
        {
            "종목명": "기아",
            "증권사": "대신증권",
            "레포트 제목": "현대차 대비 할인율 52%",
            "발행일자": "2026-05-20",
            "목표주가": "260,000원",
            "평가방식": "SOTP(사업부문별 가치합산)",
            "투자포인트": [
                "목표주가를 260,000원으로 상향 조정하며, SOTP(사업부문별 가치합산) 방식으로 산출된 목표 기업가치는 103조 원",
                "현대차 대비 52%에 달하는 과도한 밸류에이션 할인 해소 및 주가 키맞추기 기대"
            ],
            "현재가": "149,400원",
            "현재시총": "583,277억",
            "Upside": 74.0,
            "목표시총": "1,015,073억",
            "source_type": "butler_works"
        },
        {
            "종목명": "현대모비스",
            "증권사": "대신증권",
            "레포트 제목": "보스턴다이나믹스 핵심 밸류체인",
            "발행일자": "2026-05-20",
            "목표주가": "730,000원",
            "평가방식": "로봇 사업 가치 반영",
            "투자포인트": [
                "투자의견 '매수' 유지, 로봇 사업 가치를 반영하여 목표주가 730,000원으로 상향",
                "보스턴다이나믹스(BD)향 액츄에이터 직접 공급을 통해 로봇 시장의 핵심 수혜주로 부상"
            ],
            "현재가": "535,000원",
            "현재시총": "485,419억",
            "Upside": 36.4,
            "목표시총": "662,347억",
            "source_type": "butler_works"
        },
        {
            "종목명": "현대차",
            "증권사": "대신증권",
            "레포트 제목": "대장주 프리미엄은 타당",
            "발행일자": "2026-05-20",
            "목표주가": "770,000원",
            "평가방식": "SOTP(자동차·로봇·SDV 가치 합산)",
            "투자포인트": [
                "목표주가 770,000원으로 상향, 자동차·로봇·SDV 가치를 합산하는 SOTP 방식으로 변경",
                "2H26부터 공장 가동, 신차 출시 등 로봇 및 SDV 모멘텀이 재개되며 Physical AI 사업 주도 기대"
            ],
            "현재가": "592,000원",
            "현재시총": "1,212,165억",
            "Upside": 30.1,
            "목표시총": "1,576,634억",
            "source_type": "butler_works"
        },
        {
            "종목명": "HL만도",
            "증권사": "대신증권",
            "레포트 제목": "자동차 주도주가 될 것",
            "발행일자": "2026-05-20",
            "목표주가": "100,000원",
            "평가방식": "성장 모멘텀 및 이익률 개선 기대",
            "투자포인트": [
                "투자의견 '매수' 유지, 목표주가 100,000원으로 상향하며 자동차 업종 내 새로운 주도주로 부상할 가능성 제시",
                "북미 BEV 선도업체의 로봇 모멘텀과 SDV(소프트웨어 중심 자동차) 전환에 따른 수혜 기대, 2026년 4%대 영업이익률 달성 전망"
            ],
            "현재가": "52,600원",
            "현재시총": "24,699억",
            "Upside": 90.1,
            "목표시총": "46,957억",
            "source_type": "butler_works"
        },
        {
            "종목명": "현대백화점",
            "증권사": "키움증권",
            "레포트 제목": "하반기 증익 전환 기대",
            "발행일자": "2026-05-19",
            "목표주가": "147,000원",
            "평가방식": "",
            "투자포인트": [
                "2분기 백화점의 견조한 이익 증가와 하반기부터 기대되는 연결 기준 영업이익 성장",
                "자회사 지누스의 실적 가시성 개선"
            ],
            "현재가": "103,800원",
            "현재시총": "22,384억",
            "Upside": 41.6,
            "목표시총": "31,700억",
            "source_type": "butler_works"
        },
        {
            "종목명": "롯데쇼핑",
            "증권사": "키움증권",
            "레포트 제목": "탄력 받은 실적 개선",
            "발행일자": "2026-05-19",
            "목표주가": "200,000원",
            "평가방식": "",
            "투자포인트": [
                "2분기 백화점 기존점 성장률 +13% 전망 등 견조한 이익 증가",
                "베트남, 유니클로의 실적 개선 기대",
                "실적 추정치 상향 반영"
            ],
            "현재가": "153,100원",
            "현재시총": "43,310억",
            "Upside": 30.6,
            "목표시총": "56,577억",
            "source_type": "butler_works"
        },
        {
            "종목명": "삼양식품",
            "증권사": "키움증권",
            "레포트 제목": "수요 호조에 대응하는 Capa 확대",
            "발행일자": "2026-05-19",
            "목표주가": "1,850,000원",
            "평가방식": "",
            "투자포인트": [
                "불닭볶음면의 글로벌 확장성을 통한 성장 기대",
                "글로벌 수요 증가에 대응하기 위한 생산능력(Capa) 확대로 2025년에도 20% 이상의 이익 성장 전망"
            ],
            "현재가": "1,357,000원",
            "현재시총": "102,223억",
            "Upside": 36.3,
            "목표시총": "139,360억",
            "source_type": "butler_works"
        },
        {
            "종목명": "KT&G",
            "증권사": "키움증권",
            "레포트 제목": "하반기 新 주주환원정책 기대",
            "발행일자": "2026-05-19",
            "목표주가": "220,000원",
            "평가방식": "",
            "투자포인트": [
                "해외 궐련 매출의 고성장 지속",
                "하반기 배당 강화를 중심으로 한 새로운 주주환원정책 발표 기대"
            ],
            "현재가": "178,200원",
            "현재시총": "184,990억",
            "Upside": 23.5,
            "목표시총": "228,383억",
            "source_type": "butler_works"
        },
        {
            "종목명": "오리온",
            "증권사": "키움증권",
            "레포트 제목": "중국 매출 성장률 회복에 주목",
            "발행일자": "2026-05-19",
            "목표주가": "175,000원",
            "평가방식": "",
            "투자포인트": [
                "중국과 베트남 법인의 매출 성장률이 두 자릿수로 회복되며 안정적인 이익 증가 전망",
                "해외법인 중심의 판매량 성장과 배당 매력"
            ],
            "현재가": "134,600원",
            "현재시총": "53,215억",
            "Upside": 30.0,
            "목표시총": "69,188억",
            "source_type": "butler_works"
        },
        {
            "종목명": "CJ제일제당",
            "증권사": "키움증권",
            "레포트 제목": "2분기부터 바이오 반등 전망",
            "발행일자": "2026-05-19",
            "목표주가": "310,000원",
            "평가방식": "",
            "투자포인트": [
                "2분기부터 메티오닌 판가 상승 효과로 바이오 부문 수익성 반등 본격화",
                "하반기 전사 실적 개선 기대"
            ],
            "현재가": "214,000원",
            "현재시총": "32,215억",
            "Upside": 44.9,
            "목표시총": "46,667억",
            "source_type": "butler_works"
        },
        {
            "종목명": "알테오젠",
            "증권사": "키움증권",
            "레포트 제목": "특허 불확실성 해소. 다음 모멘텀은?",
            "발행일자": "2026-05-19",
            "목표주가": null,
            "평가방식": "",
            "투자포인트": [
                "미국 특허심판원의 할로자임 특허 무효 판단으로 머크와의 SC 제형 기술 관련 특허 불확실성 해소",
                "키트루다SC의 순조로운 시장 침투로 향후 3년 내 1.5조 원 규모의 판매 마일스톤 수령 기대"
            ],
            "현재가": "359,500원",
            "현재시총": "192,642억",
            "source_type": "butler_works"
        },
        {
            "종목명": "유한양행",
            "증권사": "키움증권",
            "레포트 제목": "렉라자 FDA 승인 전 주가 수준",
            "발행일자": "2026-05-19",
            "목표주가": "110,000원",
            "평가방식": "",
            "투자포인트": [
                "렉라자 FDA 승인 전 수준으로 회귀한 주가는 과도하며, 알러지 치료제 기술이전과 렉라자 데이터 발표 등 신규 모멘텀 기대",
                "투자의견 'BUY'와 목표주가 110,000원을 유지, '26년 영업이익은 '24년 대비 두 배 이상 성장 전망"
            ],
            "현재가": "81,500원",
            "현재시총": "64,912억",
            "Upside": 35.0,
            "목표시총": "87,612억",
            "source_type": "butler_works"
        },
        {
            "종목명": "에스티팜",
            "증권사": "키움증권",
            "레포트 제목": "서구권과 중화권 RNA 개발사 모두의 선택",
            "발행일자": "2026-05-19",
            "목표주가": "190,000원",
            "평가방식": "",
            "투자포인트": [
                "RNA 상업화 경험을 바탕으로 글로벌 빅파마 및 중국 개발사로부터 생산 문의가 증가하는 독보적 입지 확보",
                "주요 RNA 치료제의 승인 및 임상 결과 발표가 임박했으며, 자체 HIV 신약의 기술 이전 기대감도 유효"
            ],
            "현재가": "124,800원",
            "현재시총": "26,018억",
            "Upside": 52.2,
            "목표시총": "39,611억",
            "source_type": "butler_works"
        },
        {
            "종목명": "앱클론",
            "증권사": "키움증권",
            "레포트 제목": "AC101은 헨리우스의 광선검(Lightsaber)",
            "발행일자": "2026-05-19",
            "목표주가": "",
            "평가방식": "",
            "투자포인트": [
                "파트너사 헨리우스, AC101(HLX22)의 임상을 7건으로 대폭 확대하며 높은 자신감 표명",
                "26년 6월 종근당 보호예수 해제에 따른 오버행 우려 완화와 하반기 ESMO 데이터 발표를 통한 주가 재평가 기대"
            ],
            "현재가": "35,900원",
            "현재시총": "7,162억",
            "source_type": "butler_works"
        },
        {
            "종목명": "지아이이노베이션",
            "증권사": "키움증권",
            "레포트 제목": "한번의 신뢰가 굉장히 클 수 있다 Not",
            "발행일자": "2026-05-19",
            "목표주가": "",
            "평가방식": "",
            "투자포인트": [
                "GI-101A, GI-301, GI-102 등 주요 파이프라인의 임상 데이터 발표 및 마일스톤 유입 기대감으로 기술이전 가능성 부각",
                "고점 대비 56% 하락한 주가 수준에서 기술이전 성공 시 신뢰 회복과 함께 주가 반등 모멘텀 확보 가능"
            ],
            "현재가": "10,360원",
            "현재시총": "6,654억",
            "source_type": "butler_works"
        },
        {
            "종목명": "카카오뱅크",
            "증권사": "NH투자증권",
            "레포트 제목": "해외와 신사업에서 찾는 기회",
            "발행일자": "2026-05-20",
            "목표주가": "31,500원",
            "평가방식": "",
            "투자포인트": [
                "정부의 가계대출 규제로 전통적 성장은 어렵지만, 해외 및 신사업 진출로 새로운 성장 동력 모색",
                "투자의견 '매수'와 목표주가 31,500원 유지, 장기적으로 낮은 자본 레버리지를 개선해 높은 기업가치 평가 기대"
            ],
            "현재가": "21,950원",
            "현재시총": "104,727억",
            "Upside": 43.5,
            "목표시총": "150,292억",
            "source_type": "butler_works"
        },
        {
            "종목명": "iM금융지주",
            "증권사": "NH투자증권",
            "레포트 제목": "빠른 속도로 정상화 중",
            "발행일자": "2026-05-20",
            "목표주가": "24,000원",
            "평가방식": "",
            "투자포인트": [
                "투자의견 'Buy', 목표주가 24,000원으로 신규 제시하며 실적, 자본비율, 주주환원의 동반 개선을 전망",
                "시중은행 전환을 통한 본격적인 실적 정상화와 비과세 배당 시행에 따른 주주환원 강화 기대"
            ],
            "현재가": "18,040원",
            "현재시총": "28,976억",
            "Upside": 33.0,
            "목표시총": "38,549억",
            "source_type": "butler_works"
        },
        {
            "종목명": "BNK금융지주",
            "증권사": "NH투자증권",
            "레포트 제목": "건전성 회복이 리레이팅 열쇠",
            "발행일자": "2026-05-20",
            "목표주가": "23,000원",
            "평가방식": "",
            "투자포인트": [
                "NH투자증권, BNK금융지주에 대해 투자의견 'Buy', 목표주가 23,000원으로 신규 커버리지 개시",
                "탄탄한 지역 기반과 비은행 포트폴리오가 강점이나, 자산 건전성 회복이 향후 주가 상승의 핵심 과제"
            ],
            "현재가": "16,700원",
            "현재시총": "51,824억",
            "Upside": 37.7,
            "목표시총": "71,375억",
            "source_type": "butler_works"
        },
        {
            "종목명": "JB금융지주",
            "증권사": "NH투자증권",
            "레포트 제목": "강소 금융지주, 향후 관건은 이원 다원화",
            "발행일자": "2026-05-20",
            "목표주가": "35,000원",
            "평가방식": "",
            "투자포인트": [
                "업계 최고 수준의 수익성 강점",
                "캐피탈 중심의 이익 구조와 증권 계열사 부재"
            ],
            "현재가": "24,950원",
            "현재시총": "46,969억",
            "Upside": 40.3,
            "목표시총": "65,888억",
            "source_type": "butler_works"
        },
        {
            "종목명": "기업은행",
            "증권사": "NH투자증권",
            "레포트 제목": "주주환원, 진전은 있지만 아쉬운 속도",
            "발행일자": "2026-05-20",
            "목표주가": "28,000원",
            "평가방식": "민간 금융지주 밸류에이션 개선 기대 반영",
            "투자포인트": [
                "2026년 첫 반기배당 시행 등 주주환원 진전",
                "민간 금융지주 대비 아쉬운 자본정책 및 주주환원 속도"
            ],
            "현재가": "20,300원",
            "현재시총": "161,877억",
            "Upside": 37.9,
            "목표시총": "223,279억",
            "source_type": "butler_works"
        },
        {
            "종목명": "우리금융지주",
            "증권사": "NH투자증권",
            "레포트 제목": "주요 금융지주로 도약 기반 마련",
            "발행일자": "2026-05-20",
            "목표주가": "45,000원",
            "평가방식": "할인율 축소 반영",
            "투자포인트": [
                "자본비율 개선",
                "동양생명·우리투자증권 등 비은행 자회사 강화"
            ],
            "현재가": "30,100원",
            "현재시총": "220,956억",
            "Upside": 49.5,
            "목표시총": "330,334억",
            "source_type": "butler_works"
        },
        {
            "종목명": "하나금융지주",
            "증권사": "NH투자증권",
            "레포트 제목": "하반기 자본비율, 자본정책 모두 Level UP",
            "발행일자": "2026-05-20",
            "목표주가": "168,000원",
            "평가방식": "할인율 축소 반영",
            "투자포인트": [
                "하반기 자본비율의 뚜렷한 반등 기대",
                "새로운 주주환원 정책 발표 기대"
            ],
            "현재가": "115,600원",
            "현재시총": "317,169억",
            "Upside": 45.3,
            "목표시총": "460,937억",
            "source_type": "butler_works"
        },
        {
            "종목명": "신한지주",
            "증권사": "NH투자증권",
            "레포트 제목": "점진적인 ROE 향상 기대",
            "발행일자": "2026-05-20",
            "목표주가": "139,000원",
            "평가방식": "PBR 할인율 축소 반영",
            "투자포인트": [
                "새로운 밸류업 계획에 따른 주주환원 확대",
                "ROE(자기자본이익률) 제고 동시 추진"
            ],
            "현재가": "94,000원",
            "현재시총": "446,175억",
            "Upside": 47.9,
            "목표시총": "659,769억",
            "source_type": "butler_works"
        },
        {
            "종목명": "KB금융",
            "증권사": "NH투자증권",
            "레포트 제목": "이제는 내재가치만큼 인정받을 때",
            "발행일자": "2026-05-20",
            "목표주가": "226,000원",
            "평가방식": "내재가치에 부합하는 시장가치 평가 기대",
            "투자포인트": [
                "우수한 자본비율",
                "8천억 원 규모의 자사주 매입/소각 통해 연간 총주주환원율 56% 달성 전망"
            ],
            "현재가": "151,700원",
            "현재시총": "565,614억",
            "Upside": 49.0,
            "목표시총": "842,642억",
            "source_type": "butler_works"
        },
        {
            "종목명": "신세계인터내셔날",
            "증권사": "미래에셋증권",
            "레포트 제목": "미니 백화점",
            "발행일자": "2026-05-20",
            "목표주가": "19,000원",
            "평가방식": "실적 추정치 상향 반영",
            "투자포인트": [
                "럭셔리 패션 및 화장품 부문의 고성장",
                "외국인 인바운드 수요 회복에 따른 큰 폭의 실적 턴어라운드 기대"
            ],
            "현재가": "13,900원",
            "현재시총": "4,863억",
            "Upside": 36.7,
            "목표시총": "6,647억",
            "source_type": "butler_works"
        },
        {
            "종목명": "신세계",
            "증권사": "키움증권",
            "레포트 제목": "하반기도 탄탄대로",
            "발행일자": "2026-05-19",
            "목표주가": "630,000원",
            "평가방식": "실적 추정치 상향 반영",
            "투자포인트": [
                "2분기 백화점의 견조한 이익 성장과 면세점의 손익 개선이 기대되며 하반기에도 고성장세가 이어질 전망"
            ],
            "현재가": "494,500원",
            "현재시총": "46,706억",
            "Upside": 27.4,
            "목표시총": "59,504억",
            "source_type": "butler_works"
        },
        {
            "종목명": "삼성에피스홀딩스",
            "증권사": "대신증권",
            "레포트 제목": "안정적 수익 구조에 신약 옵션을 더하다",
            "발행일자": "2026-05-20",
            "목표주가": "620,000원",
            "평가방식": "안정적인 바이오시밀러 사업과 신약 파이프라인 가치 반영",
            "투자포인트": [
                "핵심 품목인 키트루다 바이오시밀러(SB27)의 상업화 성공과 ADC 신약 개발 진척이 향후 기업가치 상승의 핵심 동력으로 작용할 전망"
            ],
            "현재가": "464,500원",
            "현재시총": "115,581억",
            "Upside": 33.5,
            "목표시총": "154,274억",
            "source_type": "butler_works"
        },
        {
            "종목명": "올릭스",
            "증권사": "다올투자증권",
            "레포트 제목": "채워지는 R&D 시간표",
            "발행일자": "2026-05-20",
            "목표주가": "",
            "평가방식": "",
            "투자포인트": [
                "asiRNA 플랫폼 기반 MASH, 비만, 탈모 등 다양한 파이프라인의 R&D 모멘텀이 2026년 하반기에 집중",
                "기존 파트너십 마일스톤 유입과 R&D 이벤트 결과에 따른 추가 기술이전(L/O)으로 기업가치 상승 기대"
            ],
            "현재가": "148,200원",
            "현재시총": "30,085억",
            "source_type": "butler_works"
        },
        {
            "종목명": "한화",
            "증권사": "흥국증권",
            "레포트 제목": "방산/조선의 성장, 재평가 지속",
            "발행일자": "2026-05-20",
            "목표주가": "185,000원",
            "평가방식": "방산/조선 부문의 성장을 바탕으로 기업가치 재평가 지속",
            "투자포인트": [
                "방산/조선 부문의 성장을 바탕으로 기업가치 재평가가 지속될 전망",
                "1분기 실적은 시장 예상을 상회했으며, 자회사들의 고른 성장으로 2026년에도 양호한 실적 지속 예상"
            ],
            "현재가": "123,000원",
            "현재시총": "86,724억",
            "Upside": 50.4,
            "목표시총": "130,439억",
            "source_type": "butler_works"
        },
        {
            "종목명": "네패스",
            "증권사": "교보증권",
            "레포트 제목": "뚜렷한 체질 개선 추이",
            "발행일자": "2026-05-20",
            "목표주가": "36,000원",
            "평가방식": "AI 시대 PMIC(전력관리반도체) 수요 확대와 수익성 개선",
            "투자포인트": [
                "AI 시대 PMIC(전력관리반도체) 수요 확대와 수익성 개선으로 뚜렷한 체질 개선 추이 기대"
            ],
            "현재가": "29,600원",
            "현재시총": "6,825억",
            "Upside": 21.6,
            "목표시총": "8,301억",
            "source_type": "butler_works"
        },
        {
            "종목명": "피에스케이",
            "증권사": "교보증권",
            "레포트 제목": "1Q26 Review 실적으로 증명한 성장",
            "발행일자": "2026-05-20",
            "목표주가": "150,000원",
            "평가방식": "실적 성장성을 바탕으로",
            "투자포인트": [
                "1Q26 컨센서스를 대폭 상회하는 최대 실적을 달성했으며, 2026년 연간 역대 최대 실적을 기록할 전망"
            ],
            "현재가": "107,000원",
            "현재시총": "30,994억",
            "Upside": 40.2,
            "목표시총": "43,450억",
            "source_type": "butler_works"
        },
        {
            "종목명": "KG이니시스",
            "증권사": "교보증권",
            "레포트 제목": "정상화된 이익 유지 + 렌탈, 할부금융, 글로벌 성장 준비",
            "발행일자": "2026-05-20",
            "목표주가": "13,000원",
            "평가방식": "PG 거래액 증가와 렌탈페이 성장에 힘입어 정상화된 이익 기조 유지",
            "투자포인트": [
                "1Q26 PG 거래액 증가와 렌탈페이 성장에 힘입어 정상화된 이익 기조를 유지하며, 자회사 이익 개선으로 26년에도 안정적 실적 성장 전망",
                "렌탈, 할부금융, 글로벌 결제 등 신사업을 통한 매출원 다변화와 주주환원 정책이 긍정적"
            ],
            "현재가": "10,070원",
            "현재시총": "2,774억",
            "Upside": 29.1,
            "목표시총": "3,582억",
            "source_type": "butler_works"
        },
        {
            "종목명": "전진건설로봇",
            "증권사": "흥국증권",
            "레포트 제목": "여전히 견조한 글로벌 수요",
            "발행일자": "2026-05-20",
            "목표주가": "65,000원",
            "평가방식": "견조한 글로벌 수요 반영",
            "투자포인트": [
                "1분기 실적 일시적 요인으로 부진했으나, 2분기부터 회복 기대",
                "견조한 글로벌 수요를 반영하여 목표주가 상향 조정"
            ],
            "현재가": "54,600원",
            "현재시총": "7,967억",
            "Upside": 19.0,
            "목표시총": "9,485억",
            "source_type": "butler_works"
        },
        {
            "종목명": "BGF리테일",
            "증권사": "유진투자증권",
            "레포트 제목": "1Q26 Review: Growth & Fun",
            "발행일자": "2026-05-20",
            "목표주가": "180,000원",
            "평가방식": "내수 소비 심리 회복 및 판관비 절감 효과 반영",
            "투자포인트": [
                "1Q26 시장 컨센서스를 상회하는 호실적 달성",
                "내수 소비 심리 회복과 판관비 절감 효과를 반영하여 목표주가 상향"
            ],
            "현재가": "133,000원",
            "현재시총": "22,987억",
            "Upside": 35.3,
            "목표시총": "31,111억",
            "source_type": "butler_works"
        },
        {
            "종목명": "에스에프에이",
            "증권사": "BNK투자증권",
            "레포트 제목": "신규 수주 활동 활발, 내용도 좋아지고 있다",
            "발행일자": "2026-05-20",
            "목표주가": "40,000원",
            "평가방식": "본사의 활발한 신규 수주 활동으로 향후 실적 개선 기대",
            "투자포인트": [
                "1Q26 실적은 자회사 수익성 악화로 기대치 하회했으나 본사의 활발한 신규 수주 활동으로 실적 개선 기대",
                "최근 주가 부진을 매수 기회로 활용 추천"
            ],
            "현재가": "28,050원",
            "현재시총": "10,072억",
            "Upside": 42.6,
            "목표시총": "14,363억",
            "source_type": "butler_works"
        },
        {
            "종목명": "롯데관광개발",
            "증권사": "하나증권",
            "레포트 제목": "다시 기대하셔도 좋습니다",
            "발행일자": "2026-05-20",
            "목표주가": "28,000원",
            "평가방식": "테이블 증가, 홀드율 상승, 롤링 사업 확대, 이자비용 감소로 사상 최대 실적 및 주가 레벨업 기대",
            "투자포인트": [
                "테이블 증가와 홀드율 상승, 롤링 사업 확대로 올해 사상 최대 실적 및 주가 레벨업 기대",
                "2024년 대비 2026년 영업이익 대폭 성장 전망",
                "하반기 리파이낸싱으로 이자비용 감소 예상"
            ],
            "현재가": "18,840원",
            "현재시총": "14,996억",
            "Upside": 48.6,
            "목표시총": "22,288억",
            "source_type": "butler_works"
        },
        {
            "종목명": "하이브",
            "증권사": "하나증권",
            "레포트 제목": "그래도 너 밖에 없다",
            "발행일자": "2026-05-20",
            "목표주가": "400,000원",
            "평가방식": "BTS 월드투어 실적 반영 및 5세대 아티스트 성과로 사상 최대 실적 기대",
            "투자포인트": [
                "BTS 월드투어 실적 반영과 5세대 아티스트의 성과로 사상 최대 실적 기대",
                "뉴진스 이슈 등 우려를 반영한 역사적 저평가 수준으로, 반등 가능성 충분"
            ],
            "현재가": "226,500원",
            "현재시총": "97,626억",
            "Upside": 76.6,
            "목표시총": "172,408억",
            "source_type": "butler_works"
        },
        {
            "종목명": "현대글로비스",
            "증권사": "상상인증권",
            "레포트 제목": "견조한 펀더와 BD 모멘텀의 콜라보",
            "발행일자": "2026-05-20",
            "목표주가": "320,000원",
            "평가방식": "선대 확대, 환율 상승 통한 안정적인 실적 방어, 해운 수익성 개선, 유통 부문 성장, 보스턴다이나믹스 상장 기대감",
            "투자포인트": [
                "지정학적 불확실성 속 선대 확대, 환율 상승 등을 통해 안정적인 실적 방어 가능",
                "해운 수익성 개선과 유통 부문 성장 기대",
                "보스턴다이나믹스 상장 기대감"
            ],
            "현재가": "210,500원",
            "현재시총": "157,875억",
            "Upside": 52.0,
            "목표시총": "240,000억",
            "source_type": "butler_works"
        },
        {
            "종목명": "팬오션",
            "증권사": "상상인증권",
            "레포트 제목": "시황 강세가 이익에 반영되는 시점",
            "발행일자": "2026-05-20",
            "목표주가": "8,000원",
            "평가방식": "실적 전망치 상향 및 해상 운임 강세에 따른 이익 개선 기대",
            "투자포인트": [
                "실적 전망치 상향을 반영해 목표주가 상향 조정",
                "2분기부터 본격적인 해상 운임 강세가 실적에 반영되며 이익 개선 기대"
            ],
            "현재가": "5,780원",
            "현재시총": "30,898억",
            "Upside": 38.4,
            "목표시총": "42,765억",
            "source_type": "butler_works"
        },
        {
            "종목명": "디아이",
            "증권사": "신한투자증권",
            "레포트 제목": "이익 레버리지 본격화",
            "발행일자": "2026-05-20",
            "목표주가": "45,000원",
            "평가방식": "",
            "투자포인트": [
                "1분기 영업이익률 17.9% 달성으로 수익성 대폭 개선, 국내 메모리 2사 고객 확보로 독점적 지위 강화",
                "2026년 매출 5,965억 원(+38.0%), 영업이익 952억 원(+160.8%)으로 이익 레버리지 효과가 본격화될 전망"
            ],
            "현재가": "28,850원",
            "현재시총": "8,164억",
            "Upside": 56.0,
            "목표시총": "12,735억",
            "source_type": "butler_works"
        },
        {
            "종목명": "한국타이어앤테크놀로지",
            "증권사": "한화투자증권",
            "레포트 제목": "이젠 열관리가 타이어에게 힘이 될 때",
            "발행일자": "2026-05-20",
            "목표주가": "84,000원",
            "평가방식": "",
            "투자포인트": [
                "열관리 부문의 실적 턴어라운드가 타이어 부문의 원자재 가격 상승 리스크를 상쇄할 것으로 기대하며 목표주가 84,000원으로 상향",
                "1분기 유럽 중심의 견조한 타이어 매출로 높은 수익성을 기록했으나, 하반기 원자재 가격 상승은 부담 요인"
            ],
            "현재가": "59,300원",
            "현재시총": "73,457억",
            "Upside": 41.7,
            "목표시총": "104,055억",
            "source_type": "butler_works"
        },
        {
            "종목명": "에이디테크놀로지",
            "증권사": "교보증권",
            "레포트 제목": "변하지 않은 중장기 성장 여력",
            "발행일자": "2026-05-20",
            "목표주가": "60,000원",
            "평가방식": "",
            "투자포인트": [
                "1분기 실적은 IP 매입 비용 선반영으로 부진했으나, 대형 프로젝트 매출이 2분기부터 인식되며 AI/HPC 수주 중심의 가파른 성장세가 기대됨",
                "2026년 신규 수주가 전년 대비 140% 수준으로 예상되는 등 뚜렷한 성장 가시성을 보유"
            ],
            "현재가": "39,400원",
            "현재시총": "5,304억",
            "Upside": 52.3,
            "목표시총": "8,077억",
            "source_type": "butler_works"
        },
        {
            "종목명": "두산테스나",
            "증권사": "교보증권",
            "레포트 제목": "파운드리 확대에 따른 강한 수혜",
            "발행일자": "2026-05-20",
            "목표주가": "190,000원",
            "평가방식": "",
            "투자포인트": [
                "삼성 파운드리 저변 확대에 따른 직접적인 수혜와 대규모 투자 공시로 2027년 본격적인 실적 성장 기대"
            ],
            "현재가": "165,600원",
            "현재시총": "32,005억",
            "Upside": 14.7,
            "목표시총": "36,721억",
            "source_type": "butler_works"
        },
        {
            "종목명": "티씨케이",
            "증권사": "교보증권",
            "레포트 제목": "전방 시장 호황과의 필연적인 동행",
            "발행일자": "2026-05-20",
            "목표주가": "360,000원",
            "평가방식": "",
            "투자포인트": [
                "AI 반도체 투자 사이클과 동행하는 핵심 수혜주로, 전방 시장 호황에 따른 견조한 성장세 지속 전망"
            ],
            "현재가": "277,500원",
            "현재시총": "31,022억",
            "Upside": 29.7,
            "목표시총": "40,245억",
            "source_type": "butler_works"
        },
        {
            "종목명": "코리아써키트",
            "증권사": "메리츠증권",
            "레포트 제목": "혼자 디스카운트 받을 이유가 없다",
            "발행일자": "2026-05-20",
            "목표주가": "112,000원",
            "평가방식": "",
            "투자포인트": [
                "FC-BGA와 SoCAMM 사업을 중심으로 한 업황 개선 기대감에 목표주가 112,000원으로 상향 조정",
                "국내 PCB 업종 내 가장 저평가된 밸류에이션 매력을 보유, 업황 개선의 직접적인 수혜가 예상되는 최선호주로 제시"
            ],
            "현재가": "89,500원",
            "현재시총": "21,464억",
            "Upside": 25.1,
            "목표시총": "26,860억",
            "source_type": "butler_works"
        },
        {
            "종목명": "신세계",
            "증권사": "NH투자증권",
            "레포트 제목": "압도적인 백화점, 더해지는 면세점",
            "발행일자": "2026-05-20",
            "목표주가": "660,000원",
            "평가방식": "",
            "투자포인트": [
                "백화점 및 면세점 실적 개선을 반영해 목표주가를 66만원으로 상향",
                "2026년 역대 최대 실적 달성이 전망되며, 자회사 가치 상승과 주주환원 정책에 대한 기대감도 긍정적"
            ],
            "현재가": "494,500원",
            "현재시총": "46,706억",
            "Upside": 33.5,
            "목표시총": "62,338억",
            "source_type": "butler_works"
        },
        {
            "종목명": "뉴엔AI",
            "증권사": "한국IR협의회",
            "레포트 제목": "소셜 리스닝 서비스 기업",
            "발행일자": "2026-05-20",
            "목표주가": null,
            "평가방식": null,
            "투자포인트": [
                "AI 기반 소셜 리스닝 기업으로, K-뷰티 산업 성장에 힘입어 2026년 매출 211억 원 및 영업이익 흑자 전환 기대",
                "기존 모니터링 도구에서 통합 분석 시스템으로 진화하며 중소기업까지 고객층을 확대하는 구조적 성장 국면에 진입"
            ],
            "현재가": "10,070원",
            "현재시총": "894억",
            "source_type": "butler_works"
        },
        {
            "종목명": "DB하이텍",
            "증권사": "상상인증권",
            "레포트 제목": "가격 상승 사이클 진입 기대",
            "발행일자": "2026-05-20",
            "목표주가": "208,000원",
            "평가방식": null,
            "투자포인트": [
                "투자의견 'BUY' 유지, 목표주가 208,000원으로 상향, 본격적인 가격(P) 상승 사이클 진입 기대",
                "2026년 연결 매출 1조 6,022억 원, 영업이익 3,553억 원 전망, 1분기 일회성 비용에도 견조한 실적 달성"
            ],
            "현재가": "162,000원",
            "현재시총": "70,477억",
            "Upside": 28.4,
            "목표시총": "90,489억",
            "source_type": "butler_works"
        },
        {
            "종목명": "삼성바이오로직스",
            "증권사": "대신증권",
            "레포트 제목": "규모의 경제가 만드는 복리 성장",
            "발행일자": "2026-05-20",
            "목표주가": "2,000,000원",
            "평가방식": null,
            "투자포인트": [
                "글로벌 최대 생산능력(CAPA)과 높은 수익성을 바탕으로 실적 가시성이 뚜렷하며, 5공장 가동으로 이익 레버리지 본격화 전망",
                "6공장 증설 및 ADC 사업 확장 등 성장 동력을 고려해 투자의견 '매수', 목표주가 2,000,000원으로 신규 분석 개시"
            ],
            "현재가": "1,337,000원",
            "현재시총": "618,910억",
            "Upside": 49.6,
            "목표시총": "925,819억",
            "source_type": "butler_works"
        },
        {
            "종목명": "에스티팜",
            "증권사": "대신증권",
            "레포트 제목": "올리고, 성장의 변곡점",
            "발행일자": "2026-05-20",
            "목표주가": "200,000원",
            "평가방식": null,
            "투자포인트": [
                "RNA 치료제 시장의 구조적 성장에 따라 올리고(RNA 원료) 수주잔고가 빠르게 증가하며 실적 가시성 확보",
                "주요 치료제의 FDA 허가 및 임상 3상 결과 발표 등 2026년 다양한 성장 촉매(catalyst)와 증설 가시화로 긍정적 주가 흐름 기대"
            ],
            "현재가": "124,800원",
            "현재시총": "26,018억",
            "Upside": 60.3,
            "목표시총": "41,695억",
            "source_type": "butler_works"
        },
        {
            "종목명": "셀트리온",
            "증권사": "대신증권",
            "레포트 제목": "이제 보이기 시작한다",
            "발행일자": "2026-05-20",
            "목표주가": "280,000원",
            "평가방식": null,
            "투자포인트": [
                "합병 관련 불확실성 해소 및 EBITDA 마진 30%대 후반 진입 전망",
                "제품 포트폴리오 확대(현재 11개→'30년 18개)에 따른 본격적인 이익 레버리지 기대"
            ],
            "현재가": "179,400원",
            "현재시총": "398,487억",
            "Upside": 56.1,
            "목표시총": "621,942억",
            "source_type": "butler_works"
        },
        {
            "종목명": "알테오젠",
            "증권사": "대신증권",
            "레포트 제목": "검증된 플랫폼, 열려 있는 Upside",
            "발행일자": "2026-05-20",
            "목표주가": "500,000원",
            "평가방식": null,
            "투자포인트": [
                "투자의견 ‘매수’, 목표주가 500,000원으로 신규 커버리지 개시, 검증된 ALT-B4 플랫폼 기반의 안정적 기술료 수익 기대",
                "키트루다SC 마일스톤 본격화 및 ADC 등 신규 약물 제형으로의 확장 가능성은 주가 재평가(리레이팅)의 핵심 동력"
            ],
            "현재가": "359,500원",
            "현재시총": "192,642억",
            "Upside": 39.1,
            "목표시총": "267,931억",
            "source_type": "butler_works"
        },
        {
            "종목명": "삼성전자",
            "증권사": "KB증권",
            "레포트 제목": "우려는 주가에 선반영",
            "발행일자": "2026-05-20",
            "목표주가": "450,000원",
            "평가방식": null,
            "투자포인트": [
                "투자의견 'Buy'와 목표주가 450,000원을 유지하며, 파업 우려 등은 주가에 선반영된 것으로 판단",
                "AI 데이터센터향 메모리 수요 강세와 가격 상승으로 2분기 영업이익이 90조 원에 달하는 등 강력한 실적 개선 전망"
            ],
            "현재가": "276,000원",
            "현재시총": "16,135,728억",
            "Upside": 63.0,
            "목표시총": "26,308,253억",
            "source_type": "butler_works"
        },
        {
            "종목명": "호전실업",
            "증권사": "SK증권",
            "레포트 제목": "의류 OEM 시장 판이 커진다",
            "발행일자": "2026-05-20",
            "목표주가": "9,500원",
            "평가방식": "",
            "투자포인트": [
                "1분기 실적은 일시적 요인으로 부진했으나, 2분기부터 이연된 실적이 반영되며 회복될 전망",
                "경쟁사 대비 현저한 저평가 상태이며, 높은 배당수익률과 긍정적인 산업 환경이 투자 매력도를 높임"
            ],
            "현재가": "7,270원",
            "현재시총": "681억",
            "Upside": 30.7,
            "목표시총": "890억",
            "source_type": "butler_works"
        },
        {
            "종목명": "케이카",
            "증권사": "SK증권",
            "레포트 제목": "생태계 완성을 위한 퍼즐 한 조각",
            "발행일자": "2026-05-20",
            "목표주가": "20,000원",
            "평가방식": "",
            "투자포인트": [
                "1Q26 실적은 소폭 감소했으나 2분기부터 수익성 개선이 기대되며, 높은 시장 점유율은 유지",
                "최대주주 변경은 KG그룹과의 시너지를 통해 긍정적이며, 높은 배당수익률은 여전히 매력적인 투자 포인트"
            ],
            "현재가": "9,740원",
            "현재시총": "4,755억",
            "Upside": 105.3,
            "목표시총": "9,764억",
            "source_type": "butler_works"
        },
        {
            "종목명": "HL만도",
            "증권사": "삼성증권",
            "레포트 제목": "전기차 2nd Wave와 로봇 생태계 형성의 수혜주",
            "발행일자": "2026-05-19",
            "목표주가": "80,000원",
            "평가방식": "",
            "투자포인트": [
                "전기차 2nd Wave와 경쟁사 부진에 따른 수혜로 목표주가를 80,000원으로 상향 조정",
                "자동차 산업의 격변기 속 스마트 섀시와 로봇 액추에이터 분야의 Top-tier 기업으로 성장 기대"
            ],
            "현재가": "52,600원",
            "현재시총": "24,699억",
            "Upside": 52.1,
            "목표시총": "37,565억",
            "source_type": "butler_works"
        },
        {
            "종목명": "OCI홀딩스",
            "증권사": "삼성증권",
            "레포트 제목": "비중국산 폴리실리콘, 핵심 안보 자산으로 위상 격상 전망",
            "발행일자": "2026-05-19",
            "목표주가": "380,000원",
            "평가방식": "",
            "투자포인트": [
                "비중국산 폴리실리콘, 전쟁 및 우주 산업 부상으로 핵심 안보 자산으로 위상 격상 전망",
                "탈중국 공급망 수요 증가에 따른 추가 증설과 장기 계약 비중 급증(40%→95%)이 예상되어 목표주가 및 BUY 의견 유지"
            ],
            "현재가": "277,500원",
            "현재시총": "51,809억",
            "Upside": 36.9,
            "목표시총": "70,946억",
            "source_type": "butler_works"
        },
        {
            "종목명": "TKG휴켐스",
            "증권사": "삼성증권",
            "레포트 제목": "탄소배출권 가치 재부각 전망",
            "발행일자": "2026-05-19",
            "목표주가": "",
            "평가방식": "",
            "투자포인트": [
                "탄소배출권 가격 급등과 4차 거래제 시행에 따른 가치 재부각 전망",
                "주요 제품의 공급 차질 및 제한적 증설로 1Q26부터 수익성 개선 및 실적 회복세 기대"
            ],
            "현재가": "17,280원",
            "현재시총": "7,063억",
            "source_type": "butler_works"
        },
        {
            "종목명": "SK스퀘어",
            "증권사": "DB증권",
            "레포트 제목": "닉스에 자사주에 이제는 배당까지",
            "발행일자": "2026-05-20",
            "목표주가": "1,450,000원",
            "평가방식": "",
            "투자포인트": [
                "SK하이닉스 지분가치 상승과 강화된 주주환원 정책을 반영해 목표주가를 145만원으로 상향",
                "자사주 매입/소각과 더불어 사상 첫 배당을 포함한 3,100억 원 규모의 2026년 주주환원 계획 발표"
            ],
            "현재가": "1,029,000원",
            "현재시총": "1,357,851억",
            "Upside": 40.9,
            "목표시총": "1,913,396억",
            "source_type": "butler_works"
        },
        {
            "종목명": "쏠리드",
            "증권사": "하나증권",
            "레포트 제목": "귀해진 저 PBR 대표 통신장비주",
            "발행일자": "2026-05-20",
            "목표주가": "30,000원",
            "평가방식": "",
            "투자포인트": [
                "투자의견 '매수'와 목표주가 30,000원 유지, 1분기 실적 부진에 따른 주가 하락은 매수 기회로 판단",
                "미국/유럽 시장 내 입지 강화와 글로벌 동종업체 대비 낮은 PBR(주가순자산비율)이 매력적인 투자 포인트"
            ],
            "현재가": "14,790원",
            "현재시총": "8,985억",
            "Upside": 102.8,
            "목표시총": "18,226억",
            "source_type": "butler_works"
        },
        {
            "종목명": "에치에프알",
            "증권사": "하나증권",
            "레포트 제목": "이번에도 AT&T에 들어갈 확률이 높습니다",
            "발행일자": "2026-05-20",
            "목표주가": "50,000원",
            "평가방식": null,
            "투자포인트": [
                "미국 주파수 경매와 중국 장비 제재에 따른 수혜 기대로 투자의견 '매수' 및 목표주가 50,000원 유지",
                "AT&T 공급 이력을 바탕으로 한 미국 시장 내 수주 기대감으로 내년도 최대 실적 전망"
            ],
            "현재가": "30,450원",
            "현재시총": "4,052억",
            "Upside": 64.2,
            "목표시총": "6,654억",
            "source_type": "butler_works"
        },
        {
            "종목명": "KT",
            "증권사": "대신증권",
            "레포트 제목": "찐배당 기업",
            "발행일자": "2026-05-20",
            "목표주가": "74,000원",
            "평가방식": null,
            "투자포인트": [
                "26년 기준 최소 주당배당금(DPS)을 2,400원으로 확대하며 주주환원 정책 강화",
                "25~28년간 1조 원 규모의 자사주 매입 및 소각 계획을 발표하여 기업가치 제고에 대한 기대감 상승"
            ],
            "현재가": "55,800원",
            "현재시총": "140,628억",
            "Upside": 32.6,
            "목표시총": "186,496억",
            "source_type": "butler_works"
        },
        {
            "종목명": "삼화콘덴서",
            "증권사": "삼성증권",
            "레포트 제목": "1Q26 Review: 예열 끝, MLCC 매출 고성장 시작",
            "발행일자": "2026-05-19",
            "목표주가": null,
            "평가방식": null,
            "투자포인트": [
                "1Q26 연결 실적은 전년과 비슷하였으나, MLCC 매출이 +24%YoY 성장하여, 매출 비중 53% 기록",
                "MLCC는 2분기부터는 가격 인상, 하반기에는 신규 Capa 가세 예상",
                "DC-Link는 현대차/기아의 하이브리드, 전기차 판매 증가 수혜 가능",
                "클라우드 투자 붐 시기를 크게 넘어서는 AI 데이터센터 투자 붐 진행 중. 2분기부터는 MLCC 1st Tier 업체의 가격 인상에 따른 낙수 효과 가능"
            ],
            "현재가": "78,600원",
            "현재시총": "8,170억",
            "source_type": "pdf"
        },
        {
            "종목명": "F&F",
            "증권사": "삼성증권",
            "레포트 제목": "Strong 1Q prompts higher full-year guidance",
            "발행일자": "2026-05-20",
            "목표주가": "90,000원",
            "평가방식": "2026년 EPS 추정치 8% 상향 조정 반영",
            "투자포인트": [
                "1분기 실적 서프라이즈 (매출액 컨센서스 6%, 영업이익 14% 상회)",
                "2026년 연간 성장률 가이던스 4~5%에서 약 7%로 상향 조정",
                "한중 소비심리 개선, 외국인 관광객 증가 및 원화 약세로 인바운드 소비 증대, 중국 자회사 액세서리 선판매 효과"
            ],
            "현재가": "76,800원",
            "현재시총": "29,419억",
            "Upside": 17.2,
            "목표시총": "34,476억",
            "source_type": "pdf"
        },
        {
            "종목명": "셀트리온",
            "증권사": "대신증권",
            "레포트 제목": "제약업 이익은 가속, 주가는 이제부터",
            "발행일자": "2026-05-20",
            "목표주가": "280,000원",
            "평가방식": "EPS 성장률 및 P/E 디스카운트를 통한 성장성 및 저평가 매력 평가",
            "투자포인트": [
                "이익 개선 가시성 부각",
                "저평가 매력 부각"
            ],
            "현재가": "179,400원",
            "현재시총": "398,487억",
            "Upside": 56.1,
            "목표시총": "621,942억",
            "source_type": "pdf"
        },
        {
            "종목명": "삼성바이오로직스",
            "증권사": "대신증권",
            "레포트 제목": "제약업 이익은 가속, 주가는 이제부터",
            "발행일자": "2026-05-20",
            "목표주가": "2,000,000원",
            "평가방식": "EPS 성장률 및 P/E 디스카운트를 통한 성장성 및 저평가 매력 평가",
            "투자포인트": [
                "항체 CDMO",
                "글로벌 바이오 밸류체인 내 차별화된 포지션"
            ],
            "현재가": "1,337,000원",
            "현재시총": "618,910억",
            "Upside": 49.6,
            "목표시총": "925,819억",
            "source_type": "pdf"
        },
        {
            "종목명": "삼성에피스홀딩스",
            "증권사": "대신증권",
            "레포트 제목": "제약업 이익은 가속, 주가는 이제부터",
            "발행일자": "2026-05-20",
            "목표주가": "620,000원",
            "평가방식": "EPS 성장률 및 P/E 디스카운트를 통한 성장성 및 저평가 매력 평가",
            "투자포인트": [
                "바이오시밀러",
                "글로벌 바이오 밸류체인 내 차별화된 포지션"
            ],
            "현재가": "464,500원",
            "현재시총": "115,581억",
            "Upside": 33.5,
            "목표시총": "154,274억",
            "source_type": "pdf"
        },
        {
            "종목명": "알테오젠",
            "증권사": "대신증권",
            "레포트 제목": "제약업 이익은 가속, 주가는 이제부터",
            "발행일자": "2026-05-20",
            "목표주가": "500,000원",
            "평가방식": "EPS 성장률 및 P/E 디스카운트를 통한 성장성 및 저평가 매력 평가",
            "투자포인트": [
                "SC제형 전환 플랫폼",
                "SC제형 전환 본격화 기대"
            ],
            "현재가": "359,500원",
            "현재시총": "192,642억",
            "Upside": 39.1,
            "목표시총": "267,931억",
            "source_type": "pdf"
        },
        {
            "종목명": "에스티팜",
            "증권사": "대신증권",
            "레포트 제목": "제약업 이익은 가속, 주가는 이제부터",
            "발행일자": "2026-05-20",
            "목표주가": "200,000원",
            "평가방식": "EPS 성장률 및 P/E 디스카운트를 통한 성장성 및 저평가 매력 평가",
            "투자포인트": [
                "RNA 원료 CDMO",
                "RNA CDMO 수주 가시성 확대"
            ],
            "현재가": "124,800원",
            "현재시총": "26,018억",
            "Upside": 60.3,
            "목표시총": "41,695억",
            "source_type": "pdf"
        },
        {
            "종목명": "NAVER",
            "증권사": "하나증권",
            "레포트 제목": "AI/인터넷/게임 Overweight: 반등의 트리거",
            "발행일자": "2026-05-20",
            "목표주가": "350,000원",
            "평가방식": "신사업(디지털자산) 성장 잠재력 기반",
            "투자포인트": [
                "디지털자산 신사업 기대"
            ],
            "현재가": "191,500원",
            "현재시총": "300,413억",
            "Upside": 82.8,
            "목표시총": "549,058억",
            "source_type": "pdf"
        },
        {
            "종목명": "카카오",
            "증권사": "하나증권",
            "레포트 제목": "AI/인터넷/게임 Overweight: 반등의 트리거",
            "발행일자": "2026-05-20",
            "목표주가": "75,000원",
            "평가방식": "신사업(디지털자산) 성장 잠재력 기반",
            "투자포인트": [
                "디지털자산 신사업 기대"
            ],
            "현재가": "40,150원",
            "현재시총": "177,338억",
            "Upside": 86.8,
            "목표시총": "331,267억",
            "source_type": "pdf"
        },
        {
            "종목명": "크래프톤",
            "증권사": "하나증권",
            "레포트 제목": "AI/인터넷/게임 Overweight: 반등의 트리거",
            "발행일자": "2026-05-20",
            "목표주가": "460,000원",
            "평가방식": "신사업(AI) 성장 잠재력 기반",
            "투자포인트": [
                "AI 신사업 기대"
            ],
            "현재가": "265,500원",
            "현재시총": "122,481억",
            "Upside": 73.3,
            "목표시총": "212,209억",
            "source_type": "pdf"
        },
        {
            "종목명": "NC",
            "증권사": "하나증권",
            "레포트 제목": "AI/인터넷/게임 Overweight: 반등의 트리거",
            "발행일자": "2026-05-20",
            "목표주가": "420,000원",
            "평가방식": "신사업(AI) 성장 잠재력 기반",
            "투자포인트": [
                "AI 신사업 기대"
            ],
            "현재가": "260,500원",
            "현재시총": "56,122억",
            "Upside": 61.2,
            "목표시총": "90,484억",
            "source_type": "pdf"
        },
        {
            "종목명": "하이브",
            "증권사": "하나증권",
            "레포트 제목": "엔터/미디어/레저: 모든 우려가 선 반영된 주가",
            "발행일자": "2026-05-20",
            "목표주가": "400,000원",
            "평가방식": "P/E 및 성장성 기반 평가",
            "투자포인트": [
                "BTS 사상 최대 실적",
                "뉴진스 컴백",
                "캣츠아이 높은 성과",
                "신인 한국/미국 걸그룹 데뷔"
            ],
            "현재가": "226,500원",
            "현재시총": "97,626억",
            "Upside": 76.6,
            "목표시총": "172,408억",
            "source_type": "pdf"
        },
        {
            "종목명": "롯데관광개발",
            "증권사": "하나증권",
            "레포트 제목": "엔터/미디어/레저: 모든 우려가 선 반영된 주가",
            "발행일자": "2026-05-20",
            "목표주가": "28,000원",
            "평가방식": "성장성 기반 평가",
            "투자포인트": [
                "구조적 성장",
                "롤링 사업 확대 가속화"
            ],
            "현재가": "18,840원",
            "현재시총": "14,996억",
            "Upside": 48.6,
            "목표시총": "22,288억",
            "source_type": "pdf"
        },
        {
            "종목명": "디아이",
            "증권사": "신한투자증권",
            "레포트 제목": "본사, 자회사 모두 성장 구간의 초입",
            "발행일자": "2026-05-20",
            "목표주가": "45,000원",
            "평가방식": "12개월 선행 P/E 기반",
            "투자포인트": [
                "1Q 실적 수익성 대폭 개선",
                "증설 초기 국면 및 국내 메모리 2사 고객사 확보",
                "독점적 점유율 (HBM 테스트 장비)",
                "반도체 장비 수주 확대",
                "이익 레버리지 효과"
            ],
            "현재가": "28,850원",
            "현재시총": "8,164억",
            "Upside": 56.0,
            "목표시총": "12,735억",
            "source_type": "pdf"
        },
        {
            "종목명": "현대차",
            "증권사": "하나증권",
            "레포트 제목": "자동차 로보틱스 사업에 대한 미국 IR 내용 정리 (현대차 Top Pick)",
            "발행일자": "2026-05-20",
            "목표주가": "660,000원",
            "평가방식": "로보틱스 상용화 가시성 강화에 따른 Valuation 상향 근거 작용",
            "투자포인트": [
                "아틀라스 로봇의 산업 현장 투입 목표 및 규격 표준화, AI 동맹, 밸류체인 구성 등 진전",
                "로보틱스 양산 관련 구체적인 로드맵 및 목표 제시, 초기 양산 위험 최소화 수요 기반 및 전략 확인"
            ],
            "현재가": "592,000원",
            "현재시총": "1,212,165억",
            "Upside": 11.5,
            "목표시총": "1,351,401억",
            "source_type": "pdf"
        },
        {
            "종목명": "기아",
            "증권사": "하나증권",
            "레포트 제목": "자동차 로보틱스 사업에 대한 미국 IR 내용 정리 (기아 Top Pick)",
            "발행일자": "2026-05-20",
            "목표주가": "210,000원",
            "평가방식": "로보틱스 상용화 가시성 강화에 따른 Valuation 상향 근거 작용",
            "투자포인트": [
                "아틀라스 로봇의 산업 현장 투입 목표 및 규격 표준화, AI 동맹, 밸류체인 구성 등 진전",
                "로보틱스 양산 관련 구체적인 로드맵 및 목표 제시, 초기 양산 위험 최소화 수요 기반 및 전략 확인"
            ],
            "현재가": "149,400원",
            "현재시총": "583,277억",
            "Upside": 40.6,
            "목표시총": "819,867억",
            "source_type": "pdf"
        },
        {
            "종목명": "현대모비스",
            "증권사": "하나증권",
            "레포트 제목": "자동차 로보틱스 사업에 대한 미국 IR 내용 정리 (현대모비스 Top Pick)",
            "발행일자": "2026-05-20",
            "목표주가": "570,000원",
            "평가방식": "로보틱스 상용화 가시성 강화에 따른 Valuation 상향 근거 작용",
            "투자포인트": [
                "아틀라스 로봇의 산업 현장 투입 목표 및 규격 표준화, AI 동맹, 밸류체인 구성 등 진전",
                "로보틱스 양산 관련 구체적인 로드맵 및 목표 제시, 초기 양산 위험 최소화 수요 기반 및 전략 확인"
            ],
            "현재가": "535,000원",
            "현재시총": "485,419억",
            "Upside": 6.5,
            "목표시총": "517,175억",
            "source_type": "pdf"
        },
        {
            "종목명": "하이브",
            "증권사": "하나증권",
            "레포트 제목": "모든 우려가 선 반영된 주가 (하이브 최선호)",
            "발행일자": "2026-05-20",
            "목표주가": "400,000원",
            "평가방식": "과거 저점으로 작용했던 역사적 저평가 구간 진입 및 P/E 30배(주가 기준 약 30만원) 반등 가능성, 극단적 저평가 해소",
            "투자포인트": [
                "BTS의 역사적인 월드 투어 실적 반영",
                "하반기 뉴진스 컴백과 캣츠아이 높은 성과, 신인 한국/미국 걸그룹 데뷔 등 3분기부터 집중된 모멘텀"
            ],
            "현재가": "226,500원",
            "현재시총": "97,626억",
            "Upside": 76.6,
            "목표시총": "172,408억",
            "source_type": "pdf"
        },
        {
            "종목명": "롯데관광개발",
            "증권사": "하나증권",
            "레포트 제목": "모든 우려가 선 반영된 주가 (롯데관광개발 최선호)",
            "발행일자": "2026-05-20",
            "목표주가": "28,000원",
            "평가방식": "구조적 성장이 이어지고 있으며, 롤링 사업 확대로 성장 모멘텀 가속화",
            "투자포인트": [
                "구조적 성장이 이어지고 있음",
                "롤링 사업 확대로 성장 모멘텀이 가속화될 전망"
            ],
            "현재가": "18,840원",
            "현재시총": "14,996억",
            "Upside": 48.6,
            "목표시총": "22,288억",
            "source_type": "pdf"
        },
        {
            "종목명": "한화엔진",
            "증권사": "상상인증권",
            "레포트 제목": "4행정 중속엔진 시장 진입 기대",
            "발행일자": "2026-05-20",
            "목표주가": "96,000원",
            "평가방식": "4행정 중속엔진 시장 진입 및 데이터센터(DC)향 발전용 시장 진출 기대, 엔진 믹스 개선과 우호적인 환율 효과에 힘입은 견조한 실적 성장 전망",
            "투자포인트": [
                "3분기부터 4행정 중속엔진 생산을 시작하며, 향후 데이터센터(DC)향 발전용 시장 진출 기대",
                "엔진 믹스 개선과 우호적인 환율 효과에 힘입어 2026년까지 견조한 실적 성장 전망"
            ],
            "현재가": "69,600원",
            "현재시총": "58,079억",
            "Upside": 37.9,
            "목표시총": "80,109억",
            "source_type": "butler_works"
        },
        {
            "종목명": "JYP Ent.",
            "증권사": "신영증권",
            "레포트 제목": "정교해진 MD 전략 확인",
            "발행일자": "2026-05-20",
            "목표주가": "100,000원",
            "평가방식": "1분기 MD 매출 급증으로 시장 기대치를 상회하는 실적 달성 및 하반기 스트레이키즈 컴백과 고도화된 MD 전략에 따른 안정적 성장 전망",
            "투자포인트": [
                "1분기, 콘서트 및 콜라보 MD(기획 상품) 매출이 85% 급증하며 시장 기대치를 대폭 상회하는 서프라이즈 실적 달성",
                "하반기 스트레이키즈 컴백과 고도화된 MD 전략에 힘입어 안정적 성장이 전망돼 투자의견 '매수'와 목표주가 100,000원 유지"
            ],
            "현재가": "59,500원",
            "현재시총": "21,141억",
            "Upside": 68.1,
            "목표시총": "35,532억",
            "source_type": "butler_works"
        },
        {
            "종목명": "HD현대중공업",
            "증권사": "상상인증권",
            "레포트 제목": "DC향 엔진 대장주",
            "발행일자": "2026-05-20",
            "목표주가": "910,000원",
            "평가방식": "데이터센터(DC)향 엔진 신규 수주 기대감, 해상 운임 강세에 따른 이익 개선 전망 및 본업 성장과 엔진 사업부의 추가 성장 가능성 긍정적 평가",
            "투자포인트": [
                "데이터센터(DC)향 엔진 신규 수주 기대감과 해상 운임 강세에 따른 이익 개선 전망",
                "투자의견 'BUY'와 목표주가 910,000원을 유지하며, 본업 성장과 엔진 사업부의 추가 성장 가능성을 긍정적으로 평가"
            ],
            "현재가": "636,000원",
            "현재시총": "667,553억",
            "Upside": 43.1,
            "목표시총": "955,147억",
            "source_type": "butler_works"
        },
        {
            "종목명": "NC",
            "증권사": "하나증권",
            "레포트 제목": "큰 형님이 돌아왔다",
            "발행일자": "2026-05-20",
            "목표주가": "420,000원",
            "평가방식": "[아이온2]와 [리니지 클래식] 성과에 기반한 구조적 성장 구간 진입 및 Just Play 인수 효과와 신작 모멘텀을 반영한 확실한 턴어라운드 기대",
            "투자포인트": [
                "투자의견 'Buy'와 목표주가 420,000원 유지, [아이온2]와 [리니지 클래식] 성과에 기반한 구조적 성장 구간 진입을 근거로 게임 섹터 최선호주로 제시",
                "2026년 실적은 Just Play 인수 효과와 신작 모멘텀을 반영해 영업이익 5,526억 원으로 대폭 상향 조정하며 확실한 턴어라운드 기대"
            ],
            "현재가": "260,500원",
            "현재시총": "56,122억",
            "Upside": 61.2,
            "목표시총": "90,484억",
            "source_type": "butler_works"
        },
        {
            "종목명": "크래프톤",
            "증권사": "하나증권",
            "레포트 제목": "PUBG ALWAYS WIN",
            "발행일자": "2026-05-20",
            "목표주가": "460,000원",
            "평가방식": "PUBG IP의 구조적 성장과 신작 성과 긍정적 평가 및 게임 사업의 견조한 실적을 바탕으로 한 피지컬 AI 분야 사업 확장을 통한 장기 성장 동력 확보 기대",
            "투자포인트": [
                "투자의견 'Buy'와 목표주가 460,000원을 유지하며, PUBG IP의 구조적 성장과 신작 성과를 긍정적으로 평가",
                "게임 사업의 견조한 실적을 바탕으로 피지컬 AI 분야로의 사업 확장을 통해 장기 성장 동력 확보 기대"
            ],
            "현재가": "265,500원",
            "현재시총": "122,481억",
            "Upside": 73.3,
            "목표시총": "212,209억",
            "source_type": "butler_works"
        },
        {
            "종목명": "NAVER",
            "증권사": "하나증권",
            "레포트 제목": "하반기 AI, 디지털자산으로 반등 도모",
            "발행일자": "2026-05-20",
            "목표주가": "350,000원",
            "평가방식": "하반기 AI 서비스의 본격적인 수익화와 두나무 인수를 통한 디지털 자산 사업 진출로 새로운 성장 동력 확보 기대 및 안정적인 광고/커머스 실적 기반의 실적 달성 전망",
            "투자포인트": [
                "하반기 AI 서비스의 본격적인 수익화와 두나무 인수를 통한 디지털 자산 사업 진출로 새로운 성장 동력 확보 기대",
                "안정적인 광고/커머스 실적을 기반으로 2026년 매출 13조 8,264억 원, 영업이익 2조 3,942억 원 달성 전망"
            ],
            "현재가": "191,500원",
            "현재시총": "300,413억",
            "Upside": 82.8,
            "목표시총": "549,058억",
            "source_type": "butler_works"
        },
        {
            "종목명": "오리온",
            "증권사": "다올투자증권",
            "레포트 제목": "더욱 돋보일 이익 창출 능력",
            "발행일자": "2026-05-20",
            "목표주가": "180,000원",
            "평가방식": "중동 전쟁 등 대외 불확실성 속에서도 견조한 이익 창출력 입증 및 국내외 주요 법인의 지속적인 수요 증가에 대응하기 위한 생산 능력(CAPA) 확대로 향후 성장 동력 확보",
            "투자포인트": [
                "중동 전쟁 등 대외 불확실성 속에서도 견조한 이익 창출력을 입증하며 투자의견 'BUY'와 목표주가 180,000원 유지",
                "국내외 주요 법인의 지속적인 수요 증가에 대응하기 위한 생산 능력(CAPA) 확대로 향후 성장 동력 확보"
            ],
            "현재가": "134,600원",
            "현재시총": "53,215억",
            "Upside": 33.7,
            "목표시총": "71,165억",
            "source_type": "butler_works"
        },
        {
            "종목명": "현대차",
            "증권사": "대신증권",
            "레포트 제목": "자동차/부품 상승의 관성",
            "발행일자": "2026-05-20",
            "목표주가": "770,000원",
            "평가방식": "SOTP 밸류에이션 (본업 + 로봇 + SDV)",
            "투자포인트": [
                "자동차 업종의 지속적인 상승 관성",
                "휴머노이드/로봇 산업의 초기 개화 및 시장 규모(TAM) 확대 기대",
                "현대차그룹의 SOTP 밸류에이션 재평가 수혜 (본업 + 로봇 + SDV)",
                "테슬라 옵티머스 Gen3 공개 및 밸류체인 모멘텀",
                "미국 로봇 산업 육성책 등 정책 모멘텀"
            ],
            "현재가": "592,000원",
            "현재시총": "1,212,165억",
            "Upside": 30.1,
            "목표시총": "1,576,634억",
            "source_type": "pdf"
        },
        {
            "종목명": "기아",
            "증권사": "대신증권",
            "레포트 제목": "자동차/부품 상승의 관성",
            "발행일자": "2026-05-20",
            "목표주가": "260,000원",
            "평가방식": "SOTP 밸류에이션 (본업 + 로봇 + SDV)",
            "투자포인트": [
                "자동차 업종의 지속적인 상승 관성",
                "휴머노이드/로봇 산업의 초기 개화 및 시장 규모(TAM) 확대 기대",
                "현대차그룹의 SOTP 밸류에이션 재평가 수혜 (본업 + 로봇 + SDV)",
                "테슬라 옵티머스 Gen3 공개 및 밸류체인 모멘텀",
                "미국 로봇 산업 육성책 등 정책 모멘텀"
            ],
            "현재가": "149,400원",
            "현재시총": "583,277억",
            "Upside": 74.0,
            "목표시총": "1,015,073억",
            "source_type": "pdf"
        },
        {
            "종목명": "현대모비스",
            "증권사": "대신증권",
            "레포트 제목": "자동차/부품 상승의 관성",
            "발행일자": "2026-05-20",
            "목표주가": "730,000원",
            "평가방식": "자동차/부품 산업 성장 관성 및 신사업 모멘텀",
            "투자포인트": [
                "자동차 업종의 지속적인 상승 관성",
                "휴머노이드/로봇 산업의 초기 개화 및 시장 규모(TAM) 확대 기대",
                "현대차그룹의 SOTP 밸류에이션 재평가 수혜",
                "테슬라 옵티머스 Gen3 공개 및 밸류체인 모멘텀",
                "미국 로봇 산업 육성책 등 정책 모멘텀"
            ],
            "현재가": "535,000원",
            "현재시총": "485,419억",
            "Upside": 36.4,
            "목표시총": "662,347억",
            "source_type": "pdf"
        },
        {
            "종목명": "HL만도",
            "증권사": "대신증권",
            "레포트 제목": "자동차/부품 상승의 관성",
            "발행일자": "2026-05-20",
            "목표주가": "100,000원",
            "평가방식": "자동차/부품 산업 성장 관성 및 신사업 모멘텀",
            "투자포인트": [
                "자동차 업종의 지속적인 상승 관성",
                "휴머노이드/로봇 산업의 초기 개화 및 시장 규모(TAM) 확대 기대",
                "테슬라 옵티머스 Gen3 공개 및 밸류체인 모멘텀",
                "미국 로봇 산업 육성책 등 정책 모멘텀"
            ],
            "현재가": "52,600원",
            "현재시총": "24,699억",
            "Upside": 90.1,
            "목표시총": "46,957억",
            "source_type": "pdf"
        },
        {
            "종목명": "에스엘",
            "증권사": "대신증권",
            "레포트 제목": "자동차/부품 상승의 관성",
            "발행일자": "2026-05-20",
            "목표주가": "86,000원",
            "평가방식": "자동차/부품 산업 성장 관성 및 신사업 모멘텀",
            "투자포인트": [
                "자동차 업종의 지속적인 상승 관성",
                "휴머노이드/로봇 산업의 초기 개화 및 시장 규모(TAM) 확대 기대",
                "테슬라 옵티머스 Gen3 공개 및 밸류체인 모멘텀",
                "미국 로봇 산업 육성책 등 정책 모멘텀"
            ],
            "현재가": "58,900원",
            "현재시총": "27,358억",
            "Upside": 46.0,
            "목표시총": "39,945억",
            "source_type": "pdf"
        },
        {
            "종목명": "현대오토에버",
            "증권사": "대신증권",
            "레포트 제목": "자동차/부품 상승의 관성",
            "발행일자": "2026-05-20",
            "목표주가": "720,000원",
            "평가방식": "자동차/부품 산업 성장 관성 및 신사업 모멘텀",
            "투자포인트": [
                "자동차 업종의 지속적인 상승 관성",
                "휴머노이드/로봇 산업의 초기 개화 및 시장 규모(TAM) 확대 기대",
                "현대차그룹의 SOTP 밸류에이션 재평가 수혜",
                "테슬라 옵티머스 Gen3 공개 및 밸류체인 모멘텀",
                "미국 로봇 산업 육성책 등 정책 모멘텀"
            ],
            "현재가": "558,000원",
            "현재시총": "153,025억",
            "Upside": 29.0,
            "목표시총": "197,452억",
            "source_type": "pdf"
        },
        {
            "종목명": "HD현대중공업",
            "증권사": "상상인증권",
            "레포트 제목": "2026 하반기전망: 점입가경",
            "발행일자": "2026-05-20",
            "목표주가": "910,000원",
            "평가방식": "상선 중심 실적 성장 및 데이터센터(DC)향 신규 수요 기대감",
            "투자포인트": [
                "상선 중심 실적 성장 지속",
                "하반기 데이터센터(DC) 관련 신규 수주 및 증설 기대감",
                "AI 및 전력수요 기반 DC향 발전용 4행정 중속엔진 수주 증가",
                "엔진 사업부 생산 능력 확장 및 신규 수주 여력 확보 노력"
            ],
            "현재가": "636,000원",
            "현재시총": "667,553억",
            "Upside": 43.1,
            "목표시총": "955,147억",
            "source_type": "pdf"
        },
        {
            "종목명": "한화엔진",
            "증권사": "상상인증권",
            "레포트 제목": "2026 하반기전망: 점입가경",
            "발행일자": "2026-05-20",
            "목표주가": "96,000원",
            "평가방식": "4행정 중속엔진 생산 개시 및 그룹사향 신규 수주 기대",
            "투자포인트": [
                "4행정 중속엔진 생산 개시",
                "그룹사향 신규 수주를 통한 빠른 레퍼런스 확보",
                "하반기 데이터센터(DC) 관련 신규 수주 및 증설 기대감"
            ],
            "현재가": "69,600원",
            "현재시총": "58,079억",
            "Upside": 37.9,
            "목표시총": "80,109억",
            "source_type": "pdf"
        },
        {
            "종목명": "팬오션",
            "증권사": "상상인증권",
            "레포트 제목": "2026 하반기전망: 점입가경",
            "발행일자": "2026-05-20",
            "목표주가": "8,000원",
            "평가방식": "벌크, 탱커 운임 호조에 따른 하반기 실적 개선 전망",
            "투자포인트": [
                "상반기 벌크, 탱커 운임 호조에 따른 하반기 실적 개선 기대",
                "탑라인 성장으로 손익 방어 가능",
                "개별 투자 포인트 발현 기대"
            ],
            "현재가": "5,780원",
            "현재시총": "30,898억",
            "Upside": 38.4,
            "목표시총": "42,765억",
            "source_type": "pdf"
        },
        {
            "종목명": "현대글로비스",
            "증권사": "상상인증권",
            "레포트 제목": "2026 하반기전망: 점입가경",
            "발행일자": "2026-05-20",
            "목표주가": "320,000원",
            "평가방식": "PCTC 손익 방어 및 BD 지분가치 재평가 기대",
            "투자포인트": [
                "하반기 유류비 전가를 통한 PCTC(자동차운반선) 손익 방어",
                "보스턴다이나믹스(BD) 지분가치 재평가 기대",
                "개별 투자 포인트 발현 기대"
            ],
            "현재가": "210,500원",
            "현재시총": "157,875억",
            "Upside": 52.0,
            "목표시총": "240,000억",
            "source_type": "pdf"
        },
        {
            "종목명": "NAVER",
            "증권사": "",
            "레포트 제목": "반등의 트리거",
            "발행일자": "2026-05-20",
            "목표주가": "350,000원",
            "평가방식": "",
            "투자포인트": [
                "본업 우려 불식",
                "신사업이 트리거",
                "디지털자산"
            ],
            "현재가": "191,500원",
            "현재시총": "300,413억",
            "Upside": 82.8,
            "목표시총": "549,058억",
            "source_type": "pdf"
        },
        {
            "종목명": "카카오",
            "증권사": "",
            "레포트 제목": "반등의 트리거",
            "발행일자": "2026-05-20",
            "목표주가": "75,000원",
            "평가방식": "",
            "투자포인트": [
                "본업 우려 불식",
                "신사업이 트리거",
                "디지털자산"
            ],
            "현재가": "40,150원",
            "현재시총": "177,338억",
            "Upside": 86.8,
            "목표시총": "331,267억",
            "source_type": "pdf"
        },
        {
            "종목명": "크래프톤",
            "증권사": "",
            "레포트 제목": "반등의 트리거",
            "발행일자": "2026-05-20",
            "목표주가": "460,000원",
            "평가방식": "",
            "투자포인트": [
                "본업 우려 불식",
                "신사업이 트리거",
                "AI"
            ],
            "현재가": "265,500원",
            "현재시총": "122,481억",
            "Upside": 73.3,
            "목표시총": "212,209억",
            "source_type": "pdf"
        },
        {
            "종목명": "NC",
            "증권사": "",
            "레포트 제목": "반등의 트리거",
            "발행일자": "2026-05-20",
            "목표주가": "420,000원",
            "평가방식": "",
            "투자포인트": [
                "본업 우려 불식",
                "신사업이 트리거",
                "AI"
            ],
            "현재가": "260,500원",
            "현재시총": "56,122억",
            "Upside": 61.2,
            "목표시총": "90,484억",
            "source_type": "pdf"
        }
    ]
}